Workbook

Sheet Paramètres
A1: PARAMÈTRES DU MODÈLE — toutes les valeurs bleues sont modifiables
A3: 1. Scénarios d'adoption
A4: Scénario | B4: Étudiants actifs | C4: Rechargement moyen (€)
A5: Faible | B5: 150 | C5: 15
A6: Moyen | B6: 300 | C6: 20
A7: Fort | B7: 450 | C7: 25
A9: 2. Comportement de rechargement
A10: Fréquence de rechargement (1 recharge toutes les X semaines) | C10: 2
A12: 3. Soirées étudiantes
A13: Participants par soirée | C13: 150
A14: Part des participants qui rechargent (%) | C14: 0.425
A15: Montant du rechargement soirée (€) | C15: 15
A16: Nombre de soirées par mois (en période scolaire) | C16: 1
A18: 4. TVA
A19: Taux de TVA appliqué aux coûts | C19: 0.2
A21: 5. Solutions de paiement
A22: Cellules jaunes = hypothèses à confirmer (pas de grille publique)
A23: Solution | B23: % par transaction | C23: Fixe par transaction (€) | D23: Abonnement HT/mois (€) | E23: Frais d'entrée HT (€)
A24: Stripe | B24: 0.015 | C24: 0.25 | D24: 0 | E24: 0
A25: Payplug | B25: 0.011 | C25: 0.25 | D25: 30 | E25: 0
A26: Lyra Collect | B26: 0.014 | C26: 0.2 | D26: 40 | E26: 99
A27: Monetico (sans abo) | B27: 0.005 | C27: 0 | D27: 0 | E27: 0
A28: Monetico (abo estimé) | B28: 0.005 | C28: 0 | D28: 20 | E28: 0
A29: SogeCommerce Lite | B29: 0.005 | C29: 0 | D29: 16 | E29: 100
A30: SogeCommerce Complet | B30: 0.005 | C30: 0 | D30: 33 | E30: 300
A31: HelloAsso | B31: 0 | C31: 0 | D31: 0 | E31: 0

Sheet Calendrier
A1: CALENDRIER SCOLAIRE — volume d'activité mois par mois
A2: Colonnes bleues modifiables : semaines de vacances, présence des cohortes (1 = présents, 0,5 = demi-mois, 0 = partis), soirée (1/0)
A4: Mois | B4: Semaines brutes | C4: Semaines vacances | D4: Semaines actives | E4: Présence 1A | F4: Présence 2A | G4: Présence 3A | H4: Facteur présence | I4: Recharges / actif | J4: Soirée (1/0) | K4: Tx soirée | L4: Tx mois (scén. moyen) | M4: Volume mois € (scén. moyen)
A5: Septembre | B5: 4 | C5: 0 | D5: =B5-C5 -> 4 | E5: 1 | F5: 1 | G5: 1 | H5: =AVERAGE(E5:G5) -> 1 | I5: =D5/FREQ_SEM*H5 -> 2 | J5: 1 | K5: =J5*SOIREE_NB*SOIREE_PART*SOIREE_PCT -> 63.75 | L5: =NB_ACTIFS_MOY*I5+K5 -> 663.75 | M5: =NB_ACTIFS_MOY*I5*MONTANT_MOY+K5*SOIREE_MONTANT -> 12956.25
A6: Octobre | B6: 4 | C6: 1 | D6: =B6-C6 -> 3 | E6: 1 | F6: 1 | G6: 1 | H6: =AVERAGE(E6:G6) -> 1 | I6: =D6/FREQ_SEM*H6 -> 1.5 | J6: 1 | K6: =J6*SOIREE_NB*SOIREE_PART*SOIREE_PCT -> 63.75 | L6: =NB_ACTIFS_MOY*I6+K6 -> 513.75 | M6: =NB_ACTIFS_MOY*I6*MONTANT_MOY+K6*SOIREE_MONTANT -> 9956.25
A7: Novembre | B7: 4 | C7: 0 | D7: =B7-C7 -> 4 | E7: 1 | F7: 1 | G7: 1 | H7: =AVERAGE(E7:G7) -> 1 | I7: =D7/FREQ_SEM*H7 -> 2 | J7: 1 | K7: =J7*SOIREE_NB*SOIREE_PART*SOIREE_PCT -> 63.75 | L7: =NB_ACTIFS_MOY*I7+K7 -> 663.75 | M7: =NB_ACTIFS_MOY*I7*MONTANT_MOY+K7*SOIREE_MONTANT -> 12956.25
A8: Décembre | B8: 4 | C8: 2 | D8: =B8-C8 -> 2 | E8: 1 | F8: 1 | G8: 1 | H8: =AVERAGE(E8:G8) -> 1 | I8: =D8/FREQ_SEM*H8 -> 1 | J8: 1 | K8: =J8*SOIREE_NB*SOIREE_PART*SOIREE_PCT -> 63.75 | L8: =NB_ACTIFS_MOY*I8+K8 -> 363.75 | M8: =NB_ACTIFS_MOY*I8*MONTANT_MOY+K8*SOIREE_MONTANT -> 6956.25
A9: Janvier | B9: 4 | C9: 0 | D9: =B9-C9 -> 4 | E9: 1 | F9: 1 | G9: 0 | H9: =AVERAGE(E9:G9) -> 0.66666667 | I9: =D9/FREQ_SEM*H9 -> 1.3333333 | J9: 1 | K9: =J9*SOIREE_NB*SOIREE_PART*SOIREE_PCT -> 63.75 | L9: =NB_ACTIFS_MOY*I9+K9 -> 463.75 | M9: =NB_ACTIFS_MOY*I9*MONTANT_MOY+K9*SOIREE_MONTANT -> 8956.25
A10: Février | B10: 4 | C10: 2 | D10: =B10-C10 -> 2 | E10: 1 | F10: 1 | G10: 0 | H10: =AVERAGE(E10:G10) -> 0.66666667 | I10: =D10/FREQ_SEM*H10 -> 0.66666667 | J10: 1 | K10: =J10*SOIREE_NB*SOIREE_PART*SOIREE_PCT -> 63.75 | L10: =NB_ACTIFS_MOY*I10+K10 -> 263.75 | M10: =NB_ACTIFS_MOY*I10*MONTANT_MOY+K10*SOIREE_MONTANT -> 4956.25
A11: Mars | B11: 4 | C11: 0 | D11: =B11-C11 -> 4 | E11: 1 | F11: 1 | G11: 0 | H11: =AVERAGE(E11:G11) -> 0.66666667 | I11: =D11/FREQ_SEM*H11 -> 1.3333333 | J11: 1 | K11: =J11*SOIREE_NB*SOIREE_PART*SOIREE_PCT -> 63.75 | L11: =NB_ACTIFS_MOY*I11+K11 -> 463.75 | M11: =NB_ACTIFS_MOY*I11*MONTANT_MOY+K11*SOIREE_MONTANT -> 8956.25
A12: Avril | B12: 4 | C12: 2 | D12: =B12-C12 -> 2 | E12: 1 | F12: 0.5 | G12: 0 | H12: =AVERAGE(E12:G12) -> 0.5 | I12: =D12/FREQ_SEM*H12 -> 0.5 | J12: 1 | K12: =J12*SOIREE_NB*SOIREE_PART*SOIREE_PCT -> 63.75 | L12: =NB_ACTIFS_MOY*I12+K12 -> 213.75 | M12: =NB_ACTIFS_MOY*I12*MONTANT_MOY+K12*SOIREE_MONTANT -> 3956.25
A13: Mai | B13: 4 | C13: 0 | D13: =B13-C13 -> 4 | E13: 1 | F13: 0 | G13: 0 | H13: =AVERAGE(E13:G13) -> 0.33333333 | I13: =D13/FREQ_SEM*H13 -> 0.66666667 | J13: 1 | K13: =J13*SOIREE_NB*SOIREE_PART*SOIREE_PCT -> 63.75 | L13: =NB_ACTIFS_MOY*I13+K13 -> 263.75 | M13: =NB_ACTIFS_MOY*I13*MONTANT_MOY+K13*SOIREE_MONTANT -> 4956.25
A14: Juin | B14: 4 | C14: 0 | D14: =B14-C14 -> 4 | E14: 0 | F14: 0 | G14: 0 | H14: =AVERAGE(E14:G14) -> 0 | I14: =D14/FREQ_SEM*H14 -> 0 | J14: 0 | K14: =J14*SOIREE_NB*SOIREE_PART*SOIREE_PCT -> 0 | L14: =NB_ACTIFS_MOY*I14+K14 -> 0 | M14: =NB_ACTIFS_MOY*I14*MONTANT_MOY+K14*SOIREE_MONTANT -> 0
A15: Juillet | B15: 4 | C15: 0 | D15: =B15-C15 -> 4 | E15: 0 | F15: 0 | G15: 0 | H15: =AVERAGE(E15:G15) -> 0 | I15: =D15/FREQ_SEM*H15 -> 0 | J15: 0 | K15: =J15*SOIREE_NB*SOIREE_PART*SOIREE_PCT -> 0 | L15: =NB_ACTIFS_MOY*I15+K15 -> 0 | M15: =NB_ACTIFS_MOY*I15*MONTANT_MOY+K15*SOIREE_MONTANT -> 0
A16: Août | B16: 4 | C16: 0 | D16: =B16-C16 -> 4 | E16: 0 | F16: 0 | G16: 0 | H16: =AVERAGE(E16:G16) -> 0 | I16: =D16/FREQ_SEM*H16 -> 0 | J16: 0 | K16: =J16*SOIREE_NB*SOIREE_PART*SOIREE_PCT -> 0 | L16: =NB_ACTIFS_MOY*I16+K16 -> 0 | M16: =NB_ACTIFS_MOY*I16*MONTANT_MOY+K16*SOIREE_MONTANT -> 0
A17: TOTAL ANNÉE | I17: =SUM(I5:I16) -> 11 | K17: =SUM(K5:K16) -> 573.75 | L17: =SUM(L5:L16) -> 3873.75 | M17: =SUM(M5:M16) -> 74606.25

Sheet Mensuel (moyen)
A1: COMPARATIF MENSUEL — scénario moyen
A2: Coût total pour les assos, mois par mois. Vert = moins cher, rouge = plus cher. Les abonnements courent aussi pendant les mois creux.
A4: Mois | B4: Transactions | C4: Volume rechargé (€) | D4: Stripe | E4: Payplug | F4: Lyra Collect | G4: Monetico (sans abo) | H4: Monetico (abo estimé) | I4: SogeCommerce Lite | J4: SogeCommerce Complet | K4: HelloAsso
A5: =Calendrier!A5 -> Septembre | B5: =Calendrier!L5 -> 663.75 | C5: =Calendrier!M5 -> 12956.25 | D5: =$C5*STRIPE_PCT+$B5*STRIPE_FIX+STRIPE_ABO+STRIPE_ENT/12 -> 360.28125 | E5: =$C5*PAYPLUG_PCT+$B5*PAYPLUG_FIX+PAYPLUG_ABO+PAYPLUG_ENT/12 -> 338.45625 | F5: =$C5*LYRA_PCT+$B5*LYRA_FIX+LYRA_ABO+LYRA_ENT/12 -> 362.3875 | G5: =$C5*MONETICO1_PCT+$B5*MONETICO1_FIX+MONETICO1_ABO+MONETICO1_ENT/12 -> 64.78125 | H5: =$C5*MONETICO2_PCT+$B5*MONETICO2_FIX+MONETICO2_ABO+MONETICO2_ENT/12 -> 84.78125 | I5: =$C5*SOGEL_PCT+$B5*SOGEL_FIX+SOGEL_ABO+SOGEL_ENT/12 -> 89.114583 | J5: =$C5*SOGEC_PCT+$B5*SOGEC_FIX+SOGEC_ABO+SOGEC_ENT/12 -> 122.78125 | K5: =$C5*HELLO_PCT+$B5*HELLO_FIX+HELLO_ABO+HELLO_ENT/12 -> 0
A6: =Calendrier!A6 -> Octobre | B6: =Calendrier!L6 -> 513.75 | C6: =Calendrier!M6 -> 9956.25 | D6: =$C6*STRIPE_PCT+$B6*STRIPE_FIX+STRIPE_ABO+STRIPE_ENT/12 -> 277.78125 | E6: =$C6*PAYPLUG_PCT+$B6*PAYPLUG_FIX+PAYPLUG_ABO+PAYPLUG_ENT/12 -> 267.95625 | F6: =$C6*LYRA_PCT+$B6*LYRA_FIX+LYRA_ABO+LYRA_ENT/12 -> 290.3875 | G6: =$C6*MONETICO1_PCT+$B6*MONETICO1_FIX+MONETICO1_ABO+MONETICO1_ENT/12 -> 49.78125 | H6: =$C6*MONETICO2_PCT+$B6*MONETICO2_FIX+MONETICO2_ABO+MONETICO2_ENT/12 -> 69.78125 | I6: =$C6*SOGEL_PCT+$B6*SOGEL_FIX+SOGEL_ABO+SOGEL_ENT/12 -> 74.114583 | J6: =$C6*SOGEC_PCT+$B6*SOGEC_FIX+SOGEC_ABO+SOGEC_ENT/12 -> 107.78125 | K6: =$C6*HELLO_PCT+$B6*HELLO_FIX+HELLO_ABO+HELLO_ENT/12 -> 0
A7: =Calendrier!A7 -> Novembre | B7: =Calendrier!L7 -> 663.75 | C7: =Calendrier!M7 -> 12956.25 | D7: =$C7*STRIPE_PCT+$B7*STRIPE_FIX+STRIPE_ABO+STRIPE_ENT/12 -> 360.28125 | E7: =$C7*PAYPLUG_PCT+$B7*PAYPLUG_FIX+PAYPLUG_ABO+PAYPLUG_ENT/12 -> 338.45625 | F7: =$C7*LYRA_PCT+$B7*LYRA_FIX+LYRA_ABO+LYRA_ENT/12 -> 362.3875 | G7: =$C7*MONETICO1_PCT+$B7*MONETICO1_FIX+MONETICO1_ABO+MONETICO1_ENT/12 -> 64.78125 | H7: =$C7*MONETICO2_PCT+$B7*MONETICO2_FIX+MONETICO2_ABO+MONETICO2_ENT/12 -> 84.78125 | I7: =$C7*SOGEL_PCT+$B7*SOGEL_FIX+SOGEL_ABO+SOGEL_ENT/12 -> 89.114583 | J7: =$C7*SOGEC_PCT+$B7*SOGEC_FIX+SOGEC_ABO+SOGEC_ENT/12 -> 122.78125 | K7: =$C7*HELLO_PCT+$B7*HELLO_FIX+HELLO_ABO+HELLO_ENT/12 -> 0
A8: =Calendrier!A8 -> Décembre | B8: =Calendrier!L8 -> 363.75 | C8: =Calendrier!M8 -> 6956.25 | D8: =$C8*STRIPE_PCT+$B8*STRIPE_FIX+STRIPE_ABO+STRIPE_ENT/12 -> 195.28125 | E8: =$C8*PAYPLUG_PCT+$B8*PAYPLUG_FIX+PAYPLUG_ABO+PAYPLUG_ENT/12 -> 197.45625 | F8: =$C8*LYRA_PCT+$B8*LYRA_FIX+LYRA_ABO+LYRA_ENT/12 -> 218.3875 | G8: =$C8*MONETICO1_PCT+$B8*MONETICO1_FIX+MONETICO1_ABO+MONETICO1_ENT/12 -> 34.78125 | H8: =$C8*MONETICO2_PCT+$B8*MONETICO2_FIX+MONETICO2_ABO+MONETICO2_ENT/12 -> 54.78125 | I8: =$C8*SOGEL_PCT+$B8*SOGEL_FIX+SOGEL_ABO+SOGEL_ENT/12 -> 59.114583 | J8: =$C8*SOGEC_PCT+$B8*SOGEC_FIX+SOGEC_ABO+SOGEC_ENT/12 -> 92.78125 | K8: =$C8*HELLO_PCT+$B8*HELLO_FIX+HELLO_ABO+HELLO_ENT/12 -> 0
A9: =Calendrier!A9 -> Janvier | B9: =Calendrier!L9 -> 463.75 | C9: =Calendrier!M9 -> 8956.25 | D9: =$C9*STRIPE_PCT+$B9*STRIPE_FIX+STRIPE_ABO+STRIPE_ENT/12 -> 250.28125 | E9: =$C9*PAYPLUG_PCT+$B9*PAYPLUG_FIX+PAYPLUG_ABO+PAYPLUG_ENT/12 -> 244.45625 | F9: =$C9*LYRA_PCT+$B9*LYRA_FIX+LYRA_ABO+LYRA_ENT/12 -> 266.3875 | G9: =$C9*MONETICO1_PCT+$B9*MONETICO1_FIX+MONETICO1_ABO+MONETICO1_ENT/12 -> 44.78125 | H9: =$C9*MONETICO2_PCT+$B9*MONETICO2_FIX+MONETICO2_ABO+MONETICO2_ENT/12 -> 64.78125 | I9: =$C9*SOGEL_PCT+$B9*SOGEL_FIX+SOGEL_ABO+SOGEL_ENT/12 -> 69.114583 | J9: =$C9*SOGEC_PCT+$B9*SOGEC_FIX+SOGEC_ABO+SOGEC_ENT/12 -> 102.78125 | K9: =$C9*HELLO_PCT+$B9*HELLO_FIX+HELLO_ABO+HELLO_ENT/12 -> 0
A10: =Calendrier!A10 -> Février | B10: =Calendrier!L10 -> 263.75 | C10: =Calendrier!M10 -> 4956.25 | D10: =$C10*STRIPE_PCT+$B10*STRIPE_FIX+STRIPE_ABO+STRIPE_ENT/12 -> 140.28125 | E10: =$C10*PAYPLUG_PCT+$B10*PAYPLUG_FIX+PAYPLUG_ABO+PAYPLUG_ENT/12 -> 150.45625 | F10: =$C10*LYRA_PCT+$B10*LYRA_FIX+LYRA_ABO+LYRA_ENT/12 -> 170.3875 | G10: =$C10*MONETICO1_PCT+$B10*MONETICO1_FIX+MONETICO1_ABO+MONETICO1_ENT/12 -> 24.78125 | H10: =$C10*MONETICO2_PCT+$B10*MONETICO2_FIX+MONETICO2_ABO+MONETICO2_ENT/12 -> 44.78125 | I10: =$C10*SOGEL_PCT+$B10*SOGEL_FIX+SOGEL_ABO+SOGEL_ENT/12 -> 49.114583 | J10: =$C10*SOGEC_PCT+$B10*SOGEC_FIX+SOGEC_ABO+SOGEC_ENT/12 -> 82.78125 | K10: =$C10*HELLO_PCT+$B10*HELLO_FIX+HELLO_ABO+HELLO_ENT/12 -> 0
A11: =Calendrier!A11 -> Mars | B11: =Calendrier!L11 -> 463.75 | C11: =Calendrier!M11 -> 8956.25 | D11: =$C11*STRIPE_PCT+$B11*STRIPE_FIX+STRIPE_ABO+STRIPE_ENT/12 -> 250.28125 | E11: =$C11*PAYPLUG_PCT+$B11*PAYPLUG_FIX+PAYPLUG_ABO+PAYPLUG_ENT/12 -> 244.45625 | F11: =$C11*LYRA_PCT+$B11*LYRA_FIX+LYRA_ABO+LYRA_ENT/12 -> 266.3875 | G11: =$C11*MONETICO1_PCT+$B11*MONETICO1_FIX+MONETICO1_ABO+MONETICO1_ENT/12 -> 44.78125 | H11: =$C11*MONETICO2_PCT+$B11*MONETICO2_FIX+MONETICO2_ABO+MONETICO2_ENT/12 -> 64.78125 | I11: =$C11*SOGEL_PCT+$B11*SOGEL_FIX+SOGEL_ABO+SOGEL_ENT/12 -> 69.114583 | J11: =$C11*SOGEC_PCT+$B11*SOGEC_FIX+SOGEC_ABO+SOGEC_ENT/12 -> 102.78125 | K11: =$C11*HELLO_PCT+$B11*HELLO_FIX+HELLO_ABO+HELLO_ENT/12 -> 0
A12: =Calendrier!A12 -> Avril | B12: =Calendrier!L12 -> 213.75 | C12: =Calendrier!M12 -> 3956.25 | D12: =$C12*STRIPE_PCT+$B12*STRIPE_FIX+STRIPE_ABO+STRIPE_ENT/12 -> 112.78125 | E12: =$C12*PAYPLUG_PCT+$B12*PAYPLUG_FIX+PAYPLUG_ABO+PAYPLUG_ENT/12 -> 126.95625 | F12: =$C12*LYRA_PCT+$B12*LYRA_FIX+LYRA_ABO+LYRA_ENT/12 -> 146.3875 | G12: =$C12*MONETICO1_PCT+$B12*MONETICO1_FIX+MONETICO1_ABO+MONETICO1_ENT/12 -> 19.78125 | H12: =$C12*MONETICO2_PCT+$B12*MONETICO2_FIX+MONETICO2_ABO+MONETICO2_ENT/12 -> 39.78125 | I12: =$C12*SOGEL_PCT+$B12*SOGEL_FIX+SOGEL_ABO+SOGEL_ENT/12 -> 44.114583 | J12: =$C12*SOGEC_PCT+$B12*SOGEC_FIX+SOGEC_ABO+SOGEC_ENT/12 -> 77.78125 | K12: =$C12*HELLO_PCT+$B12*HELLO_FIX+HELLO_ABO+HELLO_ENT/12 -> 0
A13: =Calendrier!A13 -> Mai | B13: =Calendrier!L13 -> 263.75 | C13: =Calendrier!M13 -> 4956.25 | D13: =$C13*STRIPE_PCT+$B13*STRIPE_FIX+STRIPE_ABO+STRIPE_ENT/12 -> 140.28125 | E13: =$C13*PAYPLUG_PCT+$B13*PAYPLUG_FIX+PAYPLUG_ABO+PAYPLUG_ENT/12 -> 150.45625 | F13: =$C13*LYRA_PCT+$B13*LYRA_FIX+LYRA_ABO+LYRA_ENT/12 -> 170.3875 | G13: =$C13*MONETICO1_PCT+$B13*MONETICO1_FIX+MONETICO1_ABO+MONETICO1_ENT/12 -> 24.78125 | H13: =$C13*MONETICO2_PCT+$B13*MONETICO2_FIX+MONETICO2_ABO+MONETICO2_ENT/12 -> 44.78125 | I13: =$C13*SOGEL_PCT+$B13*SOGEL_FIX+SOGEL_ABO+SOGEL_ENT/12 -> 49.114583 | J13: =$C13*SOGEC_PCT+$B13*SOGEC_FIX+SOGEC_ABO+SOGEC_ENT/12 -> 82.78125 | K13: =$C13*HELLO_PCT+$B13*HELLO_FIX+HELLO_ABO+HELLO_ENT/12 -> 0
A14: =Calendrier!A14 -> Juin | B14: =Calendrier!L14 -> 0 | C14: =Calendrier!M14 -> 0 | D14: =$C14*STRIPE_PCT+$B14*STRIPE_FIX+STRIPE_ABO+STRIPE_ENT/12 -> 0 | E14: =$C14*PAYPLUG_PCT+$B14*PAYPLUG_FIX+PAYPLUG_ABO+PAYPLUG_ENT/12 -> 30 | F14: =$C14*LYRA_PCT+$B14*LYRA_FIX+LYRA_ABO+LYRA_ENT/12 -> 48.25 | G14: =$C14*MONETICO1_PCT+$B14*MONETICO1_FIX+MONETICO1_ABO+MONETICO1_ENT/12 -> 0 | H14: =$C14*MONETICO2_PCT+$B14*MONETICO2_FIX+MONETICO2_ABO+MONETICO2_ENT/12 -> 20 | I14: =$C14*SOGEL_PCT+$B14*SOGEL_FIX+SOGEL_ABO+SOGEL_ENT/12 -> 24.333333 | J14: =$C14*SOGEC_PCT+$B14*SOGEC_FIX+SOGEC_ABO+SOGEC_ENT/12 -> 58 | K14: =$C14*HELLO_PCT+$B14*HELLO_FIX+HELLO_ABO+HELLO_ENT/12 -> 0
A15: =Calendrier!A15 -> Juillet | B15: =Calendrier!L15 -> 0 | C15: =Calendrier!M15 -> 0 | D15: =$C15*STRIPE_PCT+$B15*STRIPE_FIX+STRIPE_ABO+STRIPE_ENT/12 -> 0 | E15: =$C15*PAYPLUG_PCT+$B15*PAYPLUG_FIX+PAYPLUG_ABO+PAYPLUG_ENT/12 -> 30 | F15: =$C15*LYRA_PCT+$B15*LYRA_FIX+LYRA_ABO+LYRA_ENT/12 -> 48.25 | G15: =$C15*MONETICO1_PCT+$B15*MONETICO1_FIX+MONETICO1_ABO+MONETICO1_ENT/12 -> 0 | H15: =$C15*MONETICO2_PCT+$B15*MONETICO2_FIX+MONETICO2_ABO+MONETICO2_ENT/12 -> 20 | I15: =$C15*SOGEL_PCT+$B15*SOGEL_FIX+SOGEL_ABO+SOGEL_ENT/12 -> 24.333333 | J15: =$C15*SOGEC_PCT+$B15*SOGEC_FIX+SOGEC_ABO+SOGEC_ENT/12 -> 58 | K15: =$C15*HELLO_PCT+$B15*HELLO_FIX+HELLO_ABO+HELLO_ENT/12 -> 0
A16: =Calendrier!A16 -> Août | B16: =Calendrier!L16 -> 0 | C16: =Calendrier!M16 -> 0 | D16: =$C16*STRIPE_PCT+$B16*STRIPE_FIX+STRIPE_ABO+STRIPE_ENT/12 -> 0 | E16: =$C16*PAYPLUG_PCT+$B16*PAYPLUG_FIX+PAYPLUG_ABO+PAYPLUG_ENT/12 -> 30 | F16: =$C16*LYRA_PCT+$B16*LYRA_FIX+LYRA_ABO+LYRA_ENT/12 -> 48.25 | G16: =$C16*MONETICO1_PCT+$B16*MONETICO1_FIX+MONETICO1_ABO+MONETICO1_ENT/12 -> 0 | H16: =$C16*MONETICO2_PCT+$B16*MONETICO2_FIX+MONETICO2_ABO+MONETICO2_ENT/12 -> 20 | I16: =$C16*SOGEL_PCT+$B16*SOGEL_FIX+SOGEL_ABO+SOGEL_ENT/12 -> 24.333333 | J16: =$C16*SOGEC_PCT+$B16*SOGEC_FIX+SOGEC_ABO+SOGEC_ENT/12 -> 58 | K16: =$C16*HELLO_PCT+$B16*HELLO_FIX+HELLO_ABO+HELLO_ENT/12 -> 0
A17: TOTAL HT | B17: =SUM(B5:B16) -> 3873.75 | C17: =SUM(C5:C16) -> 74606.25 | D17: =SUM(D5:D16) -> 2087.5312 | E17: =SUM(E5:E16) -> 2149.1062 | F17: =SUM(F5:F16) -> 2398.2375 | G17: =SUM(G5:G16) -> 373.03125 | H17: =SUM(H5:H16) -> 613.03125 | I17: =SUM(I5:I16) -> 665.03125 | ... K17: =SUM(K5:K16) -> 0
A18: TOTAL TTC | D18: =D17*(1+TVA) -> 2505.0375 | E18: =E17*(1+TVA) -> 2578.9275 | F18: =F17*(1+TVA) -> 2877.885 | G18: =G17*(1+TVA) -> 447.6375 | H18: =H17*(1+TVA) -> 735.6375 | I18: =I17*(1+TVA) -> 798.0375 | J18: =J17*(1+TVA) -> 1282.8375 | K18: =K17*(1+TVA) -> 0
A21: Décomposition annuelle des coûts (HT)
A22: Poste | B22: Stripe | C22: Payplug | D22: Lyra Collect | E22: Monetico (sans abo) | F22: Monetico (abo estimé) | G22: SogeCommerce Lite | H22: SogeCommerce Complet | I22: HelloAsso
A23: Frais variables (% + fixe/tx) | B23: =$C$17*STRIPE_PCT+$B$17*STRIPE_FIX -> 2087.5312 | C23: =$C$17*PAYPLUG_PCT+$B$17*PAYPLUG_FIX -> 1789.1063 | D23: =$C$17*LYRA_PCT+$B$17*LYRA_FIX -> 1819.2375 | E23: =$C$17*MONETICO1_PCT+$B$17*MONETICO1_FIX -> 373.03125 | F23: =$C$17*MONETICO2_PCT+$B$17*MONETICO2_FIX -> 373.03125 | G23: =$C$17*SOGEL_PCT+$B$17*SOGEL_FIX -> 373.03125 | H23: =$C$17*SOGEC_PCT+$B$17*SOGEC_FIX -> 373.03125 | I23: =$C$17*HELLO_PCT+$B$17*HELLO_FIX -> 0
A24: Abonnements (12 mois) | B24: =STRIPE_ABO*12 -> 0 | C24: =PAYPLUG_ABO*12 -> 360 | D24: =LYRA_ABO*12 -> 480 | E24: =MONETICO1_ABO*12 -> 0 | F24: =MONETICO2_ABO*12 -> 240 | G24: =SOGEL_ABO*12 -> 192 | H24: =SOGEC_ABO*12 -> 396 | I24: =HELLO_ABO*12 -> 0
A25: Frais d'entrée (année 1) | B25: =STRIPE_ENT -> 0 | C25: =PAYPLUG_ENT -> 0 | D25: =LYRA_ENT -> 99 | E25: =MONETICO1_ENT -> 0 | F25: =MONETICO2_ENT -> 0 | G25: =SOGEL_ENT -> 100 | H25: =SOGEC_ENT -> 300 | I25: =HELLO_ENT -> 0
A26: TOTAL HT année 1 | B26: =SUM(B23:B25) -> 2087.5312 | C26: =SUM(C23:C25) -> 2149.1062 | D26: =SUM(D23:D25) -> 2398.2375 | E26: =SUM(E23:E25) -> 373.03125 | F26: =SUM(F23:F25) -> 613.03125 | G26: =SUM(G23:G25) -> 665.03125 | H26: =SUM(H23:H25) -> 1069.0312 | I26: =SUM(I23:I25) -> 0

Sheet Annuel (3 scénarios)
A1: COMPARATIF ANNUEL — 3 scénarios d'adoption
A3: Scénario Faible
A4: Transactions / an | B4: =NB_ACTIFS_FAIBLE*TXPA_AN+SOIREETX_AN -> 2223.75 | D4: Volume rechargé / an | E4: =NB_ACTIFS_FAIBLE*TXPA_AN*MONTANT_FAIBLE+SOIREETX_AN*SOIREE_MONTANT -> 33356.25
A5: Solution | B5: Coût variable HT | C5: Abonnements HT | D5: Entrée HT | E5: Total HT | F5: Total TTC | G5: Coût / transaction | H5: Coût pour 1 € encaissé | I5: Rang
A6: Stripe | B6: =$E$4*STRIPE_PCT+$B$4*STRIPE_FIX -> 1056.2812 | C6: =STRIPE_ABO*12 -> 0 | D6: =STRIPE_ENT -> 0 | E6: =SUM(B6:D6) -> 1056.2812 | F6: =E6*(1+TVA) -> 1267.5375 | G6: =E6/$B$4 -> 0.475 | H6: =E6/$E$4 -> 0.031666667 | I6: =RANK(E6,$E$6:$E$13,1) -> 6
A7: Payplug | B7: =$E$4*PAYPLUG_PCT+$B$4*PAYPLUG_FIX -> 922.85625 | C7: =PAYPLUG_ABO*12 -> 360 | D7: =PAYPLUG_ENT -> 0 | E7: =SUM(B7:D7) -> 1282.8563 | F7: =E7*(1+TVA) -> 1539.4275 | G7: =E7/$B$4 -> 0.5768887 | H7: =E7/$E$4 -> 0.038459247 | I7: =RANK(E7,$E$6:$E$13,1) -> 7
A8: Lyra Collect | B8: =$E$4*LYRA_PCT+$B$4*LYRA_FIX -> 911.7375 | C8: =LYRA_ABO*12 -> 480 | D8: =LYRA_ENT -> 99 | E8: =SUM(B8:D8) -> 1490.7375 | F8: =E8*(1+TVA) -> 1788.885 | G8: =E8/$B$4 -> 0.67037099 | H8: =E8/$E$4 -> 0.0446914 | I8: =RANK(E8,$E$6:$E$13,1) -> 8
A9: Monetico (sans abo) | B9: =$E$4*MONETICO1_PCT+$B$4*MONETICO1_FIX -> 166.78125 | C9: =MONETICO1_ABO*12 -> 0 | D9: =MONETICO1_ENT -> 0 | E9: =SUM(B9:D9) -> 166.78125 | F9: =E9*(1+TVA) -> 200.1375 | G9: =E9/$B$4 -> 0.075 | H9: =E9/$E$4 -> 0.005 | I9: =RANK(E9,$E$6:$E$13,1) -> 2
A10: Monetico (abo estimé) | B10: =$E$4*MONETICO2_PCT+$B$4*MONETICO2_FIX -> 166.78125 | C10: =MONETICO2_ABO*12 -> 240 | D10: =MONETICO2_ENT -> 0 | E10: =SUM(B10:D10) -> 406.78125 | F10: =E10*(1+TVA) -> 488.1375 | G10: =E10/$B$4 -> 0.1829258 | H10: =E10/$E$4 -> 0.012195053 | I10: =RANK(E10,$E$6:$E$13,1) -> 3
A11: SogeCommerce Lite | B11: =$E$4*SOGEL_PCT+$B$4*SOGEL_FIX -> 166.78125 | C11: =SOGEL_ABO*12 -> 192 | D11: =SOGEL_ENT -> 100 | E11: =SUM(B11:D11) -> 458.78125 | F11: =E11*(1+TVA) -> 550.5375 | G11: =E11/$B$4 -> 0.20630972 | H11: =E11/$E$4 -> 0.013753982 | I11: =RANK(E11,$E$6:$E$13,1) -> 4
A12: SogeCommerce Complet | B12: =$E$4*SOGEC_PCT+$B$4*SOGEC_FIX -> 166.78125 | C12: =SOGEC_ABO*12 -> 396 | D12: =SOGEC_ENT -> 300 | E12: =SUM(B12:D12) -> 862.78125 | F12: =E12*(1+TVA) -> 1035.3375 | G12: =E12/$B$4 -> 0.38798482 | H12: =E12/$E$4 -> 0.025865655 | I12: =RANK(E12,$E$6:$E$13,1) -> 5
A13: HelloAsso | B13: =$E$4*HELLO_PCT+$B$4*HELLO_FIX -> 0 | C13: =HELLO_ABO*12 -> 0 | D13: =HELLO_ENT -> 0 | E13: =SUM(B13:D13) -> 0 | F13: =E13*(1+TVA) -> 0 | G13: =E13/$B$4 -> 0 | H13: =E13/$E$4 -> 0 | I13: =RANK(E13,$E$6:$E$13,1) -> 1
A15: Scénario Moyen
A16: Transactions / an | B16: =NB_ACTIFS_MOY*TXPA_AN+SOIREETX_AN -> 3873.75 | D16: Volume rechargé / an | E16: =NB_ACTIFS_MOY*TXPA_AN*MONTANT_MOY+SOIREETX_AN*SOIREE_MONTANT -> 74606.25
A17: Solution | B17: Coût variable HT | C17: Abonnements HT | D17: Entrée HT | E17: Total HT | F17: Total TTC | G17: Coût / transaction | H17: Coût pour 1 € encaissé | I17: Rang
A18: Stripe | B18: =$E$16*STRIPE_PCT+$B$16*STRIPE_FIX -> 2087.5312 | C18: =STRIPE_ABO*12 -> 0 | D18: =STRIPE_ENT -> 0 | E18: =SUM(B18:D18) -> 2087.5312 | F18: =E18*(1+TVA) -> 2505.0375 | G18: =E18/$B$16 -> 0.53889158 | H18: =E18/$E$16 -> 0.027980648 | I18: =RANK(E18,$E$18:$E$25,1) -> 6
A19: Payplug | B19: =$E$16*PAYPLUG_PCT+$B$16*PAYPLUG_FIX -> 1789.1063 | C19: =PAYPLUG_ABO*12 -> 360 | D19: =PAYPLUG_ENT -> 0 | E19: =SUM(B19:D19) -> 2149.1062 | F19: =E19*(1+TVA) -> 2578.9275 | G19: =E19/$B$16 -> 0.55478703 | H19: =E19/$E$16 -> 0.028805981 | I19: =RANK(E19,$E$18:$E$25,1) -> 7
A20: Lyra Collect | B20: =$E$16*LYRA_PCT+$B$16*LYRA_FIX -> 1819.2375 | C20: =LYRA_ABO*12 -> 480 | D20: =LYRA_ENT -> 99 | E20: =SUM(B20:D20) -> 2398.2375 | F20: =E20*(1+TVA) -> 2877.885 | G20: =E20/$B$16 -> 0.61909971 | H20: =E20/$E$16 -> 0.032145263 | I20: =RANK(E20,$E$18:$E$25,1) -> 8
A21: Monetico (sans abo) | B21: =$E$16*MONETICO1_PCT+$B$16*MONETICO1_FIX -> 373.03125 | C21: =MONETICO1_ABO*12 -> 0 | D21: =MONETICO1_ENT -> 0 | E21: =SUM(B21:D21) -> 373.03125 | F21: =E21*(1+TVA) -> 447.6375 | G21: =E21/$B$16 -> 0.096297193 | H21: =E21/$E$16 -> 0.005 | I21: =RANK(E21,$E$18:$E$25,1) -> 2
A22: Monetico (abo estimé) | B22: =$E$16*MONETICO2_PCT+$B$16*MONETICO2_FIX -> 373.03125 | C22: =MONETICO2_ABO*12 -> 240 | D22: =MONETICO2_ENT -> 0 | E22: =SUM(B22:D22) -> 613.03125 | F22: =E22*(1+TVA) -> 735.6375 | G22: =E22/$B$16 -> 0.15825266 | H22: =E22/$E$16 -> 0.0082168887 | I22: =RANK(E22,$E$18:$E$25,1) -> 3
A23: SogeCommerce Lite | B23: =$E$16*SOGEL_PCT+$B$16*SOGEL_FIX -> 373.03125 | C23: =SOGEL_ABO*12 -> 192 | D23: =SOGEL_ENT -> 100 | E23: =SUM(B23:D23) -> 665.03125 | F23: =E23*(1+TVA) -> 798.0375 | G23: =E23/$B$16 -> 0.17167635 | H23: =E23/$E$16 -> 0.0089138812 | I23: =RANK(E23,$E$18:$E$25,1) -> 4
A24: SogeCommerce Complet | B24: =$E$16*SOGEC_PCT+$B$16*SOGEC_FIX -> 373.03125 | C24: =SOGEC_ABO*12 -> 396 | D24: =SOGEC_ENT -> 300 | E24: =SUM(B24:D24) -> 1069.0312 | F24: =E24*(1+TVA) -> 1282.8375 | G24: =E24/$B$16 -> 0.27596805 | H24: =E24/$E$16 -> 0.014328977 | I24: =RANK(E24,$E$18:$E$25,1) -> 5
A25: HelloAsso | B25: =$E$16*HELLO_PCT+$B$16*HELLO_FIX -> 0 | C25: =HELLO_ABO*12 -> 0 | D25: =HELLO_ENT -> 0 | E25: =SUM(B25:D25) -> 0 | F25: =E25*(1+TVA) -> 0 | G25: =E25/$B$16 -> 0 | H25: =E25/$E$16 -> 0 | I25: =RANK(E25,$E$18:$E$25,1) -> 1
A27: Scénario Fort
A28: Transactions / an | B28: =NB_ACTIFS_FORT*TXPA_AN+SOIREETX_AN -> 5523.75 | D28: Volume rechargé / an | E28: =NB_ACTIFS_FORT*TXPA_AN*MONTANT_FORT+SOIREETX_AN*SOIREE_MONTANT -> 132356.25
A29: Solution | B29: Coût variable HT | C29: Abonnements HT | D29: Entrée HT | E29: Total HT | F29: Total TTC | G29: Coût / transaction | H29: Coût pour 1 € encaissé | I29: Rang
A30: Stripe | B30: =$E$28*STRIPE_PCT+$B$28*STRIPE_FIX -> 3366.2812 | C30: =STRIPE_ABO*12 -> 0 | D30: =STRIPE_ENT -> 0 | E30: =SUM(B30:D30) -> 3366.2812 | F30: =E30*(1+TVA) -> 4039.5375 | G30: =E30/$B$28 -> 0.60941955 | H30: =E30/$E$28 -> 0.025433489 | I30: =RANK(E30,$E$30:$E$37,1) -> 7
A31: Payplug | B31: =$E$28*PAYPLUG_PCT+$B$28*PAYPLUG_FIX -> 2836.8562 | C31: =PAYPLUG_ABO*12 -> 360 | D31: =PAYPLUG_ENT -> 0 | E31: =SUM(B31:D31) -> 3196.8562 | F31: =E31*(1+TVA) -> 3836.2275 | G31: =E31/$B$28 -> 0.57874745 | H31: =E31/$E$28 -> 0.024153421 | I31: =RANK(E31,$E$30:$E$37,1) -> 6
A32: Lyra Collect | B32: =$E$28*LYRA_PCT+$B$28*LYRA_FIX -> 2957.7375 | C32: =LYRA_ABO*12 -> 480 | D32: =LYRA_ENT -> 99 | E32: =SUM(B32:D32) -> 3536.7375 | F32: =E32*(1+TVA) -> 4244.085 | G32: =E32/$B$28 -> 0.64027834 | H32: =E32/$E$28 -> 0.026721349 | I32: =RANK(E32,$E$30:$E$37,1) -> 8
A33: Monetico (sans abo) | B33: =$E$28*MONETICO1_PCT+$B$28*MONETICO1_FIX -> 661.78125 | C33: =MONETICO1_ABO*12 -> 0 | D33: =MONETICO1_ENT -> 0 | E33: =SUM(B33:D33) -> 661.78125 | F33: =E33*(1+TVA) -> 794.1375 | G33: =E33/$B$28 -> 0.11980652 | H33: =E33/$E$28 -> 0.005 | I33: =RANK(E33,$E$30:$E$37,1) -> 2
A34: Monetico (abo estimé) | B34: =$E$28*MONETICO2_PCT+$B$28*MONETICO2_FIX -> 661.78125 | C34: =MONETICO2_ABO*12 -> 240 | D34: =MONETICO2_ENT -> 0 | E34: =SUM(B34:D34) -> 901.78125 | F34: =E34*(1+TVA) -> 1082.1375 | G34: =E34/$B$28 -> 0.16325526 | H34: =E34/$E$28 -> 0.006813288 | I34: =RANK(E34,$E$30:$E$37,1) -> 3
A35: SogeCommerce Lite | B35: =$E$28*SOGEL_PCT+$B$28*SOGEL_FIX -> 661.78125 | C35: =SOGEL_ABO*12 -> 192 | D35: =SOGEL_ENT -> 100 | E35: =SUM(B35:D35) -> 953.78125 | F35: =E35*(1+TVA) -> 1144.5375 | G35: =E35/$B$28 -> 0.17266916 | H35: =E35/$E$28 -> 0.0072061671 | I35: =RANK(E35,$E$30:$E$37,1) -> 4
A36: SogeCommerce Complet | B36: =$E$28*SOGEC_PCT+$B$28*SOGEC_FIX -> 661.78125 | C36: =SOGEC_ABO*12 -> 396 | D36: =SOGEC_ENT -> 300 | E36: =SUM(B36:D36) -> 1357.7812 | F36: =E36*(1+TVA) -> 1629.3375 | G36: =E36/$B$28 -> 0.24580788 | H36: =E36/$E$28 -> 0.010258535 | I36: =RANK(E36,$E$30:$E$37,1) -> 5
A37: HelloAsso | B37: =$E$28*HELLO_PCT+$B$28*HELLO_FIX -> 0 | C37: =HELLO_ABO*12 -> 0 | D37: =HELLO_ENT -> 0 | E37: =SUM(B37:D37) -> 0 | F37: =E37*(1+TVA) -> 0 | G37: =E37/$B$28 -> 0 | H37: =E37/$E$28 -> 0 | I37: =RANK(E37,$E$30:$E$37,1) -> 1
A40: Synthèse Total TTC (source graphique)
A41: Scénario | B41: Stripe | C41: Payplug | D41: Lyra Collect | E41: Monetico (sans abo) | F41: Monetico (abo estimé) | G41: SogeCommerce Lite | H41: SogeCommerce Complet | I41: HelloAsso
A42: Faible | B42: =F6 -> 1267.5375 | C42: =F7 -> 1539.4275 | D42: =F8 -> 1788.885 | E42: =F9 -> 200.1375 | F42: =F10 -> 488.1375 | G42: =F11 -> 550.5375 | H42: =F12 -> 1035.3375 | I42: =F13 -> 0
A43: Moyen | B43: =F18 -> 2505.0375 | C43: =F19 -> 2578.9275 | D43: =F20 -> 2877.885 | E43: =F21 -> 447.6375 | F43: =F22 -> 735.6375 | G43: =F23 -> 798.0375 | H43: =F24 -> 1282.8375 | I43: =F25 -> 0
A44: Fort | B44: =F30 -> 4039.5375 | C44: =F31 -> 3836.2275 | D44: =F32 -> 4244.085 | E44: =F33 -> 794.1375 | F44: =F34 -> 1082.1375 | G44: =F35 -> 1144.5375 | H44: =F36 -> 1629.3375 | I44: =F37 -> 0

Sheet Point d'équilibre
A1: POINT D'ÉQUILIBRE — à partir de quel volume une solution à abonnement bat Stripe ?
A2: Hypothèse : transactions au panier moyen du scénario moyen. Économie par transaction = ce que la solution fait gagner par rapport à Stripe.
A4: Solution | B4: Coût fixe mensuel HT (abo + entrée/12) | C4: Économie par transaction vs Stripe | D4: Transactions / mois pour l'équilibre | E4: Volume € / mois pour l'équilibre | F4: Étudiants actifs équivalents
A5: Payplug | B5: =PAYPLUG_ABO+PAYPLUG_ENT/12 -> 30 | C5: =(STRIPE_PCT-PAYPLUG_PCT)*MONTANT_MOY+(STRIPE_FIX-PAYPLUG_FIX) -> 0.08 | D5: =IFERROR(IF(C5<=0,"jamais",B5/C5),"-") -> 375 | E5: =IFERROR(IF(C5<=0,"-",D5*MONTANT_MOY),"-") -> 7500 | F5: =IFERROR(IF(C5<=0,"-",D5/(4/FREQ_SEM)),"-") -> 187.5
A6: Lyra Collect | B6: =LYRA_ABO+LYRA_ENT/12 -> 48.25 | C6: =(STRIPE_PCT-LYRA_PCT)*MONTANT_MOY+(STRIPE_FIX-LYRA_FIX) -> 0.07 | D6: =IFERROR(IF(C6<=0,"jamais",B6/C6),"-") -> 689.28571 | E6: =IFERROR(IF(C6<=0,"-",D6*MONTANT_MOY),"-") -> 13785.714 | F6: =IFERROR(IF(C6<=0,"-",D6/(4/FREQ_SEM)),"-") -> 344.64286
A7: Monetico (abo estimé) | B7: =MONETICO2_ABO+MONETICO2_ENT/12 -> 20 | C7: =(STRIPE_PCT-MONETICO2_PCT)*MONTANT_MOY+(STRIPE_FIX-MONETICO2_FIX) -> 0.45 | D7: =IFERROR(IF(C7<=0,"jamais",B7/C7),"-") -> 44.444444 | E7: =IFERROR(IF(C7<=0,"-",D7*MONTANT_MOY),"-") -> 888.88889 | F7: =IFERROR(IF(C7<=0,"-",D7/(4/FREQ_SEM)),"-") -> 22.222222
A8: SogeCommerce Lite | B8: =SOGEL_ABO+SOGEL_ENT/12 -> 24.333333 | C8: =(STRIPE_PCT-SOGEL_PCT)*MONTANT_MOY+(STRIPE_FIX-SOGEL_FIX) -> 0.45 | D8: =IFERROR(IF(C8<=0,"jamais",B8/C8),"-") -> 54.074074 | E8: =IFERROR(IF(C8<=0,"-",D8*MONTANT_MOY),"-") -> 1081.4815 | F8: =IFERROR(IF(C8<=0,"-",D8/(4/FREQ_SEM)),"-") -> 27.037037
A9: SogeCommerce Complet | B9: =SOGEC_ABO+SOGEC_ENT/12 -> 58 | C9: =(STRIPE_PCT-SOGEC_PCT)*MONTANT_MOY+(STRIPE_FIX-SOGEC_FIX) -> 0.45 | D9: =IFERROR(IF(C9<=0,"jamais",B9/C9),"-") -> 128.88889 | E9: =IFERROR(IF(C9<=0,"-",D9*MONTANT_MOY),"-") -> 2577.7778 | F9: =IFERROR(IF(C9<=0,"-",D9/(4/FREQ_SEM)),"-") -> 64.444444
A11: Lecture : avec un panier moyen de 20 €, il faut ce nombre de transactions par mois pour que l'abonnement soit amorti par les frais plus bas.
A13: Coût mensuel HT en fonction du nombre de transactions (source graphiques)
A14: Transactions / mois | B14: Stripe | C14: Payplug | D14: Lyra Collect
A15: 0 | B15: =A15*(STRIPE_PCT*MONTANT_MOY+STRIPE_FIX) -> 0 | C15: =A15*(PAYPLUG_PCT*MONTANT_MOY+PAYPLUG_FIX)+PAYPLUG_ABO+PAYPLUG_ENT/12 -> 30 | D15: =A15*(LYRA_PCT*MONTANT_MOY+LYRA_FIX)+LYRA_ABO+LYRA_ENT/12 -> 48.25
A16: 100 | B16: =A16*(STRIPE_PCT*MONTANT_MOY+STRIPE_FIX) -> 55 | C16: =A16*(PAYPLUG_PCT*MONTANT_MOY+PAYPLUG_FIX)+PAYPLUG_ABO+PAYPLUG_ENT/12 -> 77 | D16: =A16*(LYRA_PCT*MONTANT_MOY+LYRA_FIX)+LYRA_ABO+LYRA_ENT/12 -> 96.25
A17: 200 | B17: =A17*(STRIPE_PCT*MONTANT_MOY+STRIPE_FIX) -> 110 | C17: =A17*(PAYPLUG_PCT*MONTANT_MOY+PAYPLUG_FIX)+PAYPLUG_ABO+PAYPLUG_ENT/12 -> 124 | D17: =A17*(LYRA_PCT*MONTANT_MOY+LYRA_FIX)+LYRA_ABO+LYRA_ENT/12 -> 144.25
A18: 300 | B18: =A18*(STRIPE_PCT*MONTANT_MOY+STRIPE_FIX) -> 165 | C18: =A18*(PAYPLUG_PCT*MONTANT_MOY+PAYPLUG_FIX)+PAYPLUG_ABO+PAYPLUG_ENT/12 -> 171 | D18: =A18*(LYRA_PCT*MONTANT_MOY+LYRA_FIX)+LYRA_ABO+LYRA_ENT/12 -> 192.25
A19: 400 | B19: =A19*(STRIPE_PCT*MONTANT_MOY+STRIPE_FIX) -> 220 | C19: =A19*(PAYPLUG_PCT*MONTANT_MOY+PAYPLUG_FIX)+PAYPLUG_ABO+PAYPLUG_ENT/12 -> 218 | D19: =A19*(LYRA_PCT*MONTANT_MOY+LYRA_FIX)+LYRA_ABO+LYRA_ENT/12 -> 240.25
A20: 500 | B20: =A20*(STRIPE_PCT*MONTANT_MOY+STRIPE_FIX) -> 275 | C20: =A20*(PAYPLUG_PCT*MONTANT_MOY+PAYPLUG_FIX)+PAYPLUG_ABO+PAYPLUG_ENT/12 -> 265 | D20: =A20*(LYRA_PCT*MONTANT_MOY+LYRA_FIX)+LYRA_ABO+LYRA_ENT/12 -> 288.25
A21: 600 | B21: =A21*(STRIPE_PCT*MONTANT_MOY+STRIPE_FIX) -> 330 | C21: =A21*(PAYPLUG_PCT*MONTANT_MOY+PAYPLUG_FIX)+PAYPLUG_ABO+PAYPLUG_ENT/12 -> 312 | D21: =A21*(LYRA_PCT*MONTANT_MOY+LYRA_FIX)+LYRA_ABO+LYRA_ENT/12 -> 336.25
A22: 700 | B22: =A22*(STRIPE_PCT*MONTANT_MOY+STRIPE_FIX) -> 385 | C22: =A22*(PAYPLUG_PCT*MONTANT_MOY+PAYPLUG_FIX)+PAYPLUG_ABO+PAYPLUG_ENT/12 -> 359 | D22: =A22*(LYRA_PCT*MONTANT_MOY+LYRA_FIX)+LYRA_ABO+LYRA_ENT/12 -> 384.25
A23: 800 | B23: =A23*(STRIPE_PCT*MONTANT_MOY+STRIPE_FIX) -> 440 | C23: =A23*(PAYPLUG_PCT*MONTANT_MOY+PAYPLUG_FIX)+PAYPLUG_ABO+PAYPLUG_ENT/12 -> 406 | D23: =A23*(LYRA_PCT*MONTANT_MOY+LYRA_FIX)+LYRA_ABO+LYRA_ENT/12 -> 432.25
A24: 900 | B24: =A24*(STRIPE_PCT*MONTANT_MOY+STRIPE_FIX) -> 495 | C24: =A24*(PAYPLUG_PCT*MONTANT_MOY+PAYPLUG_FIX)+PAYPLUG_ABO+PAYPLUG_ENT/12 -> 453 | D24: =A24*(LYRA_PCT*MONTANT_MOY+LYRA_FIX)+LYRA_ABO+LYRA_ENT/12 -> 480.25
A25: 1000 | B25: =A25*(STRIPE_PCT*MONTANT_MOY+STRIPE_FIX) -> 550 | C25: =A25*(PAYPLUG_PCT*MONTANT_MOY+PAYPLUG_FIX)+PAYPLUG_ABO+PAYPLUG_ENT/12 -> 500 | D25: =A25*(LYRA_PCT*MONTANT_MOY+LYRA_FIX)+LYRA_ABO+LYRA_ENT/12 -> 528.25

Sheet Graphiques
A1: GRAPHIQUES — tous liés aux feuilles de calcul, mis à jour automatiquement

Sheet Résumé
A1: RÉSUMÉ & RECOMMANDATION — basé sur le scénario moyen, mis à jour automatiquement
A3: Solution | B3: Coût annuel TTC (scén. moyen) | C3: Rang | D3: Verdict | E3: Point fort | F3: Point de vigilance
A4: Stripe | B4: ='Annuel (3 scénarios)'!F18 -> 2505.0375 | C4: =RANK(B4,$B$4:$B$11,1) -> 6 | D4: =IF(C4=1,"Recommandé",IF(C4<=3,"À étudier","Plus coûteux")) -> Plus coûteux | E4: API excellente, sandbox immédiate, aucun coût fixe | F4: Acteur américain, frais légèrement plus élevés
A5: Payplug | B5: ='Annuel (3 scénarios)'!F19 -> 2578.9275 | C5: =RANK(B5,$B$4:$B$11,1) -> 7 | D5: =IF(C5=1,"Recommandé",IF(C5<=3,"À étudier","Plus coûteux")) -> Plus coûteux | E5: Frais les plus bas des PSP classiques sur cartes FR | F5: Abonnement dû même les mois creux ; entrée à confirmer
A6: Lyra Collect | B6: ='Annuel (3 scénarios)'!F20 -> 2877.885 | C6: =RANK(B6,$B$4:$B$11,1) -> 8 | D6: =IF(C6=1,"Recommandé",IF(C6<=3,"À étudier","Plus coûteux")) -> Plus coûteux | E6: Acteur français historique, API complète | F6: Abonnement + entrée ; minimum mensuel à négocier
A7: Monetico (sans abo) | B7: ='Annuel (3 scénarios)'!F21 -> 447.6375 | C7: =RANK(B7,$B$4:$B$11,1) -> 2 | D7: =IF(C7=1,"Recommandé",IF(C7<=3,"À étudier","Plus coûteux")) -> À étudier | E7: Commission potentiellement très basse | F7: Nécessite un compte CM/CIC ; taux à confirmer (hypothèse)
A8: Monetico (abo estimé) | B8: ='Annuel (3 scénarios)'!F22 -> 735.6375 | C8: =RANK(B8,$B$4:$B$11,1) -> 3 | D8: =IF(C8=1,"Recommandé",IF(C8<=3,"À étudier","Plus coûteux")) -> À étudier | E8: Commission basse + relation bancaire intégrée | F8: Nécessite un compte CM/CIC ; abo et taux à confirmer
A9: SogeCommerce Lite | B9: ='Annuel (3 scénarios)'!F23 -> 798.0375 | C9: =RANK(B9,$B$4:$B$11,1) -> 4 | D9: =IF(C9=1,"Recommandé",IF(C9<=3,"À étudier","Plus coûteux")) -> Plus coûteux | E9: Abonnement le plus bas des offres bancaires | F9: Nécessite un compte Société Générale ; taux hypothèse
A10: SogeCommerce Complet | B10: ='Annuel (3 scénarios)'!F24 -> 1282.8375 | C10: =RANK(B10,$B$4:$B$11,1) -> 5 | D10: =IF(C10=1,"Recommandé",IF(C10<=3,"À étudier","Plus coûteux")) -> Plus coûteux | E10: Offre complète avec boutique en ligne | F10: Frais d'entrée 300 € ; nécessite compte SG
A11: HelloAsso | B11: ='Annuel (3 scénarios)'!F25 -> 0 | C11: =RANK(B11,$B$4:$B$11,1) -> 1 | D11: =IF(C11=1,"Recommandé",IF(C11<=3,"À étudier","Plus coûteux")) -> Recommandé | E11: Totalement gratuit pour les associations | F11: CGU à valider pour le cas wallet ; écran pourboire imposé
A14: Recommandation automatique (solution la moins chère du scénario moyen) :
A15: =INDEX(A4:A11,MATCH(MIN(B4:B11),B4:B11,0))&" — "&TEXT(MIN(B4:B11),"# ##0")&" € TTC/an. Vérifier les points de vigilance avant décision." -> HelloAsso — 0 € TTC/an. Vérifier les points de vigilance avant décision.
A17: Note : les cellules jaunes de la feuille Paramètres sont des hypothèses (Monetico, SogeCommerce). Les verdicts se recalculent si vous les modifiez.
