Workbook

Sheet Paramètres
A1: PARAMÈTRES DU PILOTE ADE — septembre 2026 à mai 2027 (9 mois)
A2: Cellules bleues = modifiables · Cellules jaunes = hypothèses à confirmer
A4: 1. Scénarios d'adoption
A5: Scénario | B5: Étudiants actifs | C5: Rechargement moyen (€)
A6: Faible | B6: 100 | C6: 15
A7: Moyen | B7: 250 | C7: 20
A8: Fort | B8: 400 | C8: 25
A10: 2. Comportement
A11: Fréquence de rechargement (1 recharge toutes les X semaines) | C11: 2
A12: Durée du pilote (mois, pour les abonnements) | C12: 9
A14: 3. Soirées BDE
A15: Participants par soirée | C15: 150
A16: Part des participants qui rechargent | C16: 0.42
A17: Montant du rechargement soirée (€) | C17: 15
A19: 4. Events Epicuria
A20: Volume rechargé par event (€) | C20: 25 | D20: Basé sur le dernier event : ~50 € dont la moitié en virement
A21: Transactions par event | C21: 2
A23: 5. TVA
A24: Taux de TVA appliqué aux coûts | C24: 0.2
A26: 6. Solutions de paiement
A27: Solution | B27: % / transaction | C27: Fixe / transaction (€) | D27: Abonnement HT/mois (€) | E27: Frais d'entrée one-shot HT (€)
A28: Stripe | B28: 0.015 | C28: 0.25 | D28: 0 | E28: 0
A29: Payplug | B29: 0.011 | C29: 0.25 | D29: 30 | E29: 0
A30: Lyra Collect | B30: 0.014 | C30: 0.2 | D30: 40 | E30: 99
A31: Monetico (sans abo) | B31: 0.005 | C31: 0 | D31: 0 | E31: 0
A32: Monetico (abo estimé) | B32: 0.005 | C32: 0 | D32: 20 | E32: 0
A33: SogeCommerce Lite | B33: 0.005 | C33: 0 | D33: 16 | E33: 100
A34: SogeCommerce Complet | B34: 0.005 | C34: 0 | D34: 33 | E34: 300
A35: HelloAsso | B35: 0 | C35: 0 | D35: 0 | E35: 0

Sheet Calendrier pilote
A1: CALENDRIER PILOTE — activité mois par mois (sept 2026 → mai 2027)
A2: Colonnes bleues modifiables : vacances, présence des cohortes, soirée BDE (1/0), event Epicuria (1/0)
A4: Mois | B4: Semaines brutes | C4: Semaines vacances | D4: Semaines actives | E4: Présence 1A | F4: Présence 2A | G4: Présence 3A | H4: Facteur présence | I4: Recharges / actif | J4: Soirée BDE (1/0) | K4: Tx soirée | L4: Vol. soirée (€) | M4: Event Epicuria (1/0) | N4: Tx Epicuria | O4: Vol. Epicuria (€) | P4: Tx total (scén. moyen) | Q4: Volume total € (scén. moyen)
A5: Septembre | B5: 4 | C5: 0 | D5: =B5-C5 -> 4 | E5: 1 | F5: 1 | G5: 1 | H5: =AVERAGE(E5:G5) -> 1 | I5: =D5/FREQ_SEM*H5 -> 2 | J5: 0 | K5: =J5*BDE_PART*BDE_PCT -> 0 | L5: =K5*BDE_MT -> 0 | M5: 0 | N5: =M5*EPI_TX -> 0 | O5: =M5*EPI_VOL -> 0 | P5: =NB_MOY*I5+K5+N5 -> 500 | Q5: =NB_MOY*I5*MT_MOY+L5+O5 -> 10000
A6: Octobre | B6: 4 | C6: 1 | D6: =B6-C6 -> 3 | E6: 1 | F6: 1 | G6: 1 | H6: =AVERAGE(E6:G6) -> 1 | I6: =D6/FREQ_SEM*H6 -> 1.5 | J6: 1 | K6: =J6*BDE_PART*BDE_PCT -> 63 | L6: =K6*BDE_MT -> 945 | M6: 1 | N6: =M6*EPI_TX -> 2 | O6: =M6*EPI_VOL -> 25 | P6: =NB_MOY*I6+K6+N6 -> 440 | Q6: =NB_MOY*I6*MT_MOY+L6+O6 -> 8470
A7: Novembre | B7: 4 | C7: 0 | D7: =B7-C7 -> 4 | E7: 1 | F7: 1 | G7: 1 | H7: =AVERAGE(E7:G7) -> 1 | I7: =D7/FREQ_SEM*H7 -> 2 | J7: 1 | K7: =J7*BDE_PART*BDE_PCT -> 63 | L7: =K7*BDE_MT -> 945 | M7: 0 | N7: =M7*EPI_TX -> 0 | O7: =M7*EPI_VOL -> 0 | P7: =NB_MOY*I7+K7+N7 -> 563 | Q7: =NB_MOY*I7*MT_MOY+L7+O7 -> 10945
A8: Décembre | B8: 4 | C8: 2 | D8: =B8-C8 -> 2 | E8: 1 | F8: 1 | G8: 1 | H8: =AVERAGE(E8:G8) -> 1 | I8: =D8/FREQ_SEM*H8 -> 1 | J8: 0 | K8: =J8*BDE_PART*BDE_PCT -> 0 | L8: =K8*BDE_MT -> 0 | M8: 1 | N8: =M8*EPI_TX -> 2 | O8: =M8*EPI_VOL -> 25 | P8: =NB_MOY*I8+K8+N8 -> 252 | Q8: =NB_MOY*I8*MT_MOY+L8+O8 -> 5025
A9: Janvier | B9: 4 | C9: 0 | D9: =B9-C9 -> 4 | E9: 1 | F9: 1 | G9: 0 | H9: =AVERAGE(E9:G9) -> 0.66666667 | I9: =D9/FREQ_SEM*H9 -> 1.3333333 | J9: 0 | K9: =J9*BDE_PART*BDE_PCT -> 0 | L9: =K9*BDE_MT -> 0 | M9: 0 | N9: =M9*EPI_TX -> 0 | O9: =M9*EPI_VOL -> 0 | P9: =NB_MOY*I9+K9+N9 -> 333.33333 | Q9: =NB_MOY*I9*MT_MOY+L9+O9 -> 6666.6667
A10: Février | B10: 4 | C10: 2 | D10: =B10-C10 -> 2 | E10: 1 | F10: 1 | G10: 0 | H10: =AVERAGE(E10:G10) -> 0.66666667 | I10: =D10/FREQ_SEM*H10 -> 0.66666667 | J10: 1 | K10: =J10*BDE_PART*BDE_PCT -> 63 | L10: =K10*BDE_MT -> 945 | M10: 0 | N10: =M10*EPI_TX -> 0 | O10: =M10*EPI_VOL -> 0 | P10: =NB_MOY*I10+K10+N10 -> 229.66667 | Q10: =NB_MOY*I10*MT_MOY+L10+O10 -> 4278.3333
A11: Mars | B11: 4 | C11: 0 | D11: =B11-C11 -> 4 | E11: 1 | F11: 1 | G11: 0 | H11: =AVERAGE(E11:G11) -> 0.66666667 | I11: =D11/FREQ_SEM*H11 -> 1.3333333 | J11: 1 | K11: =J11*BDE_PART*BDE_PCT -> 63 | L11: =K11*BDE_MT -> 945 | M11: 1 | N11: =M11*EPI_TX -> 2 | O11: =M11*EPI_VOL -> 25 | P11: =NB_MOY*I11+K11+N11 -> 398.33333 | Q11: =NB_MOY*I11*MT_MOY+L11+O11 -> 7636.6667
A12: Avril | B12: 4 | C12: 2 | D12: =B12-C12 -> 2 | E12: 1 | F12: 0.5 | G12: 0 | H12: =AVERAGE(E12:G12) -> 0.5 | I12: =D12/FREQ_SEM*H12 -> 0.5 | J12: 0 | K12: =J12*BDE_PART*BDE_PCT -> 0 | L12: =K12*BDE_MT -> 0 | M12: 0 | N12: =M12*EPI_TX -> 0 | O12: =M12*EPI_VOL -> 0 | P12: =NB_MOY*I12+K12+N12 -> 125 | Q12: =NB_MOY*I12*MT_MOY+L12+O12 -> 2500
A13: Mai | B13: 4 | C13: 0 | D13: =B13-C13 -> 4 | E13: 1 | F13: 0 | G13: 0 | H13: =AVERAGE(E13:G13) -> 0.33333333 | I13: =D13/FREQ_SEM*H13 -> 0.66666667 | J13: 0 | K13: =J13*BDE_PART*BDE_PCT -> 0 | L13: =K13*BDE_MT -> 0 | M13: 0 | N13: =M13*EPI_TX -> 0 | O13: =M13*EPI_VOL -> 0 | P13: =NB_MOY*I13+K13+N13 -> 166.66667 | Q13: =NB_MOY*I13*MT_MOY+L13+O13 -> 3333.3333
A14: TOTAL PILOTE | I14: =SUM(I5:I13) -> 11 | K14: =SUM(K5:K13) -> 252 | L14: =SUM(L5:L13) -> 3780 | N14: =SUM(N5:N13) -> 6 | O14: =SUM(O5:O13) -> 75 | P14: =SUM(P5:P13) -> 3008 | Q14: =SUM(Q5:Q13) -> 58855

Sheet Mensuel (moyen)
A1: COMPARATIF MENSUEL — scénario moyen · les frais d'entrée sont payés en septembre (one-shot)
A3: Mois | B3: Transactions | C3: Volume (€) | D3: Stripe | E3: Payplug | F3: Lyra Collect | G3: Monetico (sans abo) | H3: Monetico (abo estimé) | I3: SogeCommerce Lite | J3: SogeCommerce Complet | K3: HelloAsso
A4: ='Calendrier pilote'!A5 -> Septembre | B4: ='Calendrier pilote'!P5 -> 500 | C4: ='Calendrier pilote'!Q5 -> 10000 | D4: =$C4*STRIPE_PCT+$B4*STRIPE_FIX+STRIPE_ABO+STRIPE_ENT -> 275 | E4: =$C4*PAYPLUG_PCT+$B4*PAYPLUG_FIX+PAYPLUG_ABO+PAYPLUG_ENT -> 265 | F4: =$C4*LYRA_PCT+$B4*LYRA_FIX+LYRA_ABO+LYRA_ENT -> 379 | G4: =$C4*MON1_PCT+$B4*MON1_FIX+MON1_ABO+MON1_ENT -> 50 | H4: =$C4*MON2_PCT+$B4*MON2_FIX+MON2_ABO+MON2_ENT -> 70 | I4: =$C4*SOGEL_PCT+$B4*SOGEL_FIX+SOGEL_ABO+SOGEL_ENT -> 166 | J4: =$C4*SOGEC_PCT+$B4*SOGEC_FIX+SOGEC_ABO+SOGEC_ENT -> 383 | K4: =$C4*HELLO_PCT+$B4*HELLO_FIX+HELLO_ABO+HELLO_ENT -> 0
A5: ='Calendrier pilote'!A6 -> Octobre | B5: ='Calendrier pilote'!P6 -> 440 | C5: ='Calendrier pilote'!Q6 -> 8470 | D5: =$C5*STRIPE_PCT+$B5*STRIPE_FIX+STRIPE_ABO -> 237.05 | E5: =$C5*PAYPLUG_PCT+$B5*PAYPLUG_FIX+PAYPLUG_ABO -> 233.17 | F5: =$C5*LYRA_PCT+$B5*LYRA_FIX+LYRA_ABO -> 246.58 | G5: =$C5*MON1_PCT+$B5*MON1_FIX+MON1_ABO -> 42.35 | H5: =$C5*MON2_PCT+$B5*MON2_FIX+MON2_ABO -> 62.35 | I5: =$C5*SOGEL_PCT+$B5*SOGEL_FIX+SOGEL_ABO -> 58.35 | J5: =$C5*SOGEC_PCT+$B5*SOGEC_FIX+SOGEC_ABO -> 75.35 | K5: =$C5*HELLO_PCT+$B5*HELLO_FIX+HELLO_ABO -> 0
A6: ='Calendrier pilote'!A7 -> Novembre | B6: ='Calendrier pilote'!P7 -> 563 | C6: ='Calendrier pilote'!Q7 -> 10945 | D6: =$C6*STRIPE_PCT+$B6*STRIPE_FIX+STRIPE_ABO -> 304.925 | E6: =$C6*PAYPLUG_PCT+$B6*PAYPLUG_FIX+PAYPLUG_ABO -> 291.145 | F6: =$C6*LYRA_PCT+$B6*LYRA_FIX+LYRA_ABO -> 305.83 | G6: =$C6*MON1_PCT+$B6*MON1_FIX+MON1_ABO -> 54.725 | H6: =$C6*MON2_PCT+$B6*MON2_FIX+MON2_ABO -> 74.725 | I6: =$C6*SOGEL_PCT+$B6*SOGEL_FIX+SOGEL_ABO -> 70.725 | J6: =$C6*SOGEC_PCT+$B6*SOGEC_FIX+SOGEC_ABO -> 87.725 | K6: =$C6*HELLO_PCT+$B6*HELLO_FIX+HELLO_ABO -> 0
A7: ='Calendrier pilote'!A8 -> Décembre | B7: ='Calendrier pilote'!P8 -> 252 | C7: ='Calendrier pilote'!Q8 -> 5025 | D7: =$C7*STRIPE_PCT+$B7*STRIPE_FIX+STRIPE_ABO -> 138.375 | E7: =$C7*PAYPLUG_PCT+$B7*PAYPLUG_FIX+PAYPLUG_ABO -> 148.275 | F7: =$C7*LYRA_PCT+$B7*LYRA_FIX+LYRA_ABO -> 160.75 | G7: =$C7*MON1_PCT+$B7*MON1_FIX+MON1_ABO -> 25.125 | H7: =$C7*MON2_PCT+$B7*MON2_FIX+MON2_ABO -> 45.125 | I7: =$C7*SOGEL_PCT+$B7*SOGEL_FIX+SOGEL_ABO -> 41.125 | J7: =$C7*SOGEC_PCT+$B7*SOGEC_FIX+SOGEC_ABO -> 58.125 | K7: =$C7*HELLO_PCT+$B7*HELLO_FIX+HELLO_ABO -> 0
A8: ='Calendrier pilote'!A9 -> Janvier | B8: ='Calendrier pilote'!P9 -> 333.33333 | C8: ='Calendrier pilote'!Q9 -> 6666.6667 | D8: =$C8*STRIPE_PCT+$B8*STRIPE_FIX+STRIPE_ABO -> 183.33333 | E8: =$C8*PAYPLUG_PCT+$B8*PAYPLUG_FIX+PAYPLUG_ABO -> 186.66667 | F8: =$C8*LYRA_PCT+$B8*LYRA_FIX+LYRA_ABO -> 200 | G8: =$C8*MON1_PCT+$B8*MON1_FIX+MON1_ABO -> 33.333333 | H8: =$C8*MON2_PCT+$B8*MON2_FIX+MON2_ABO -> 53.333333 | I8: =$C8*SOGEL_PCT+$B8*SOGEL_FIX+SOGEL_ABO -> 49.333333 | J8: =$C8*SOGEC_PCT+$B8*SOGEC_FIX+SOGEC_ABO -> 66.333333 | K8: =$C8*HELLO_PCT+$B8*HELLO_FIX+HELLO_ABO -> 0
A9: ='Calendrier pilote'!A10 -> Février | B9: ='Calendrier pilote'!P10 -> 229.66667 | C9: ='Calendrier pilote'!Q10 -> 4278.3333 | D9: =$C9*STRIPE_PCT+$B9*STRIPE_FIX+STRIPE_ABO -> 121.59167 | E9: =$C9*PAYPLUG_PCT+$B9*PAYPLUG_FIX+PAYPLUG_ABO -> 134.47833 | F9: =$C9*LYRA_PCT+$B9*LYRA_FIX+LYRA_ABO -> 145.83 | G9: =$C9*MON1_PCT+$B9*MON1_FIX+MON1_ABO -> 21.391667 | H9: =$C9*MON2_PCT+$B9*MON2_FIX+MON2_ABO -> 41.391667 | I9: =$C9*SOGEL_PCT+$B9*SOGEL_FIX+SOGEL_ABO -> 37.391667 | J9: =$C9*SOGEC_PCT+$B9*SOGEC_FIX+SOGEC_ABO -> 54.391667 | K9: =$C9*HELLO_PCT+$B9*HELLO_FIX+HELLO_ABO -> 0
A10: ='Calendrier pilote'!A11 -> Mars | B10: ='Calendrier pilote'!P11 -> 398.33333 | C10: ='Calendrier pilote'!Q11 -> 7636.6667 | D10: =$C10*STRIPE_PCT+$B10*STRIPE_FIX+STRIPE_ABO -> 214.13333 | E10: =$C10*PAYPLUG_PCT+$B10*PAYPLUG_FIX+PAYPLUG_ABO -> 213.58667 | F10: =$C10*LYRA_PCT+$B10*LYRA_FIX+LYRA_ABO -> 226.58 | G10: =$C10*MON1_PCT+$B10*MON1_FIX+MON1_ABO -> 38.183333 | H10: =$C10*MON2_PCT+$B10*MON2_FIX+MON2_ABO -> 58.183333 | I10: =$C10*SOGEL_PCT+$B10*SOGEL_FIX+SOGEL_ABO -> 54.183333 | J10: =$C10*SOGEC_PCT+$B10*SOGEC_FIX+SOGEC_ABO -> 71.183333 | K10: =$C10*HELLO_PCT+$B10*HELLO_FIX+HELLO_ABO -> 0
A11: ='Calendrier pilote'!A12 -> Avril | B11: ='Calendrier pilote'!P12 -> 125 | C11: ='Calendrier pilote'!Q12 -> 2500 | D11: =$C11*STRIPE_PCT+$B11*STRIPE_FIX+STRIPE_ABO -> 68.75 | E11: =$C11*PAYPLUG_PCT+$B11*PAYPLUG_FIX+PAYPLUG_ABO -> 88.75 | F11: =$C11*LYRA_PCT+$B11*LYRA_FIX+LYRA_ABO -> 100 | G11: =$C11*MON1_PCT+$B11*MON1_FIX+MON1_ABO -> 12.5 | H11: =$C11*MON2_PCT+$B11*MON2_FIX+MON2_ABO -> 32.5 | I11: =$C11*SOGEL_PCT+$B11*SOGEL_FIX+SOGEL_ABO -> 28.5 | J11: =$C11*SOGEC_PCT+$B11*SOGEC_FIX+SOGEC_ABO -> 45.5 | K11: =$C11*HELLO_PCT+$B11*HELLO_FIX+HELLO_ABO -> 0
A12: ='Calendrier pilote'!A13 -> Mai | B12: ='Calendrier pilote'!P13 -> 166.66667 | C12: ='Calendrier pilote'!Q13 -> 3333.3333 | D12: =$C12*STRIPE_PCT+$B12*STRIPE_FIX+STRIPE_ABO -> 91.666667 | E12: =$C12*PAYPLUG_PCT+$B12*PAYPLUG_FIX+PAYPLUG_ABO -> 108.33333 | F12: =$C12*LYRA_PCT+$B12*LYRA_FIX+LYRA_ABO -> 120 | G12: =$C12*MON1_PCT+$B12*MON1_FIX+MON1_ABO -> 16.666667 | H12: =$C12*MON2_PCT+$B12*MON2_FIX+MON2_ABO -> 36.666667 | I12: =$C12*SOGEL_PCT+$B12*SOGEL_FIX+SOGEL_ABO -> 32.666667 | J12: =$C12*SOGEC_PCT+$B12*SOGEC_FIX+SOGEC_ABO -> 49.666667 | K12: =$C12*HELLO_PCT+$B12*HELLO_FIX+HELLO_ABO -> 0
A13: TOTAL HT | B13: =SUM(B4:B12) -> 3008 | C13: =SUM(C4:C12) -> 58855 | D13: =SUM(D4:D12) -> 1634.825 | E13: =SUM(E4:E12) -> 1669.405 | F13: =SUM(F4:F12) -> 1884.57 | G13: =SUM(G4:G12) -> 294.275 | H13: =SUM(H4:H12) -> 474.275 | I13: =SUM(I4:I12) -> 538.275 | ... K13: =SUM(K4:K12) -> 0
A14: TOTAL TTC | D14: =D13*(1+TVA) -> 1961.79 | E14: =E13*(1+TVA) -> 2003.286 | F14: =F13*(1+TVA) -> 2261.484 | G14: =G13*(1+TVA) -> 353.13 | H14: =H13*(1+TVA) -> 569.13 | I14: =I13*(1+TVA) -> 645.93 | J14: =J13*(1+TVA) -> 1069.53 | K14: =K13*(1+TVA) -> 0

Sheet Total pilote (3 scénarios)
A1: COÛT TOTAL DU PILOTE — 9 mois, frais d'entrée inclus en réel (one-shot)
A3: Scénario Faible
A4: Transactions pilote | B4: =NB_FAIBLE*TXPA_TOT+BDETX_TOT+EPITX_TOT -> 1358 | D4: Volume rechargé pilote | E4: =NB_FAIBLE*TXPA_TOT*MT_FAIBLE+BDEVOL_TOT+EPIVOL_TOT -> 20355
A5: Solution | B5: Coût variable HT | C5: Abonnements HT (9 mois) | D5: Entrée one-shot HT | E5: Total HT | F5: Total TTC | G5: Rang
A6: Stripe | B6: =$E$4*STRIPE_PCT+$B$4*STRIPE_FIX -> 644.825 | C6: =STRIPE_ABO*NB_MOIS -> 0 | D6: =STRIPE_ENT -> 0 | E6: =SUM(B6:D6) -> 644.825 | F6: =E6*(1+TVA) -> 773.79 | G6: =RANK(E6,$E$6:$E$13,1) -> 5
A7: Payplug | B7: =$E$4*PAYPLUG_PCT+$B$4*PAYPLUG_FIX -> 563.405 | C7: =PAYPLUG_ABO*NB_MOIS -> 270 | D7: =PAYPLUG_ENT -> 0 | E7: =SUM(B7:D7) -> 833.405 | F7: =E7*(1+TVA) -> 1000.086 | G7: =RANK(E7,$E$6:$E$13,1) -> 7
A8: Lyra Collect | B8: =$E$4*LYRA_PCT+$B$4*LYRA_FIX -> 556.57 | C8: =LYRA_ABO*NB_MOIS -> 360 | D8: =LYRA_ENT -> 99 | E8: =SUM(B8:D8) -> 1015.57 | F8: =E8*(1+TVA) -> 1218.684 | G8: =RANK(E8,$E$6:$E$13,1) -> 8
A9: Monetico (sans abo) | B9: =$E$4*MON1_PCT+$B$4*MON1_FIX -> 101.775 | C9: =MON1_ABO*NB_MOIS -> 0 | D9: =MON1_ENT -> 0 | E9: =SUM(B9:D9) -> 101.775 | F9: =E9*(1+TVA) -> 122.13 | G9: =RANK(E9,$E$6:$E$13,1) -> 2
A10: Monetico (abo estimé) | B10: =$E$4*MON2_PCT+$B$4*MON2_FIX -> 101.775 | C10: =MON2_ABO*NB_MOIS -> 180 | D10: =MON2_ENT -> 0 | E10: =SUM(B10:D10) -> 281.775 | F10: =E10*(1+TVA) -> 338.13 | G10: =RANK(E10,$E$6:$E$13,1) -> 3
A11: SogeCommerce Lite | B11: =$E$4*SOGEL_PCT+$B$4*SOGEL_FIX -> 101.775 | C11: =SOGEL_ABO*NB_MOIS -> 144 | D11: =SOGEL_ENT -> 100 | E11: =SUM(B11:D11) -> 345.775 | F11: =E11*(1+TVA) -> 414.93 | G11: =RANK(E11,$E$6:$E$13,1) -> 4
A12: SogeCommerce Complet | B12: =$E$4*SOGEC_PCT+$B$4*SOGEC_FIX -> 101.775 | C12: =SOGEC_ABO*NB_MOIS -> 297 | D12: =SOGEC_ENT -> 300 | E12: =SUM(B12:D12) -> 698.775 | F12: =E12*(1+TVA) -> 838.53 | G12: =RANK(E12,$E$6:$E$13,1) -> 6
A13: HelloAsso | B13: =$E$4*HELLO_PCT+$B$4*HELLO_FIX -> 0 | C13: =HELLO_ABO*NB_MOIS -> 0 | D13: =HELLO_ENT -> 0 | E13: =SUM(B13:D13) -> 0 | F13: =E13*(1+TVA) -> 0 | G13: =RANK(E13,$E$6:$E$13,1) -> 1
A15: Scénario Moyen
A16: Transactions pilote | B16: =NB_MOY*TXPA_TOT+BDETX_TOT+EPITX_TOT -> 3008 | D16: Volume rechargé pilote | E16: =NB_MOY*TXPA_TOT*MT_MOY+BDEVOL_TOT+EPIVOL_TOT -> 58855
A17: Solution | B17: Coût variable HT | C17: Abonnements HT (9 mois) | D17: Entrée one-shot HT | E17: Total HT | F17: Total TTC | G17: Rang
A18: Stripe | B18: =$E$16*STRIPE_PCT+$B$16*STRIPE_FIX -> 1634.825 | C18: =STRIPE_ABO*NB_MOIS -> 0 | D18: =STRIPE_ENT -> 0 | E18: =SUM(B18:D18) -> 1634.825 | F18: =E18*(1+TVA) -> 1961.79 | G18: =RANK(E18,$E$18:$E$25,1) -> 6
A19: Payplug | B19: =$E$16*PAYPLUG_PCT+$B$16*PAYPLUG_FIX -> 1399.405 | C19: =PAYPLUG_ABO*NB_MOIS -> 270 | D19: =PAYPLUG_ENT -> 0 | E19: =SUM(B19:D19) -> 1669.405 | F19: =E19*(1+TVA) -> 2003.286 | G19: =RANK(E19,$E$18:$E$25,1) -> 7
A20: Lyra Collect | B20: =$E$16*LYRA_PCT+$B$16*LYRA_FIX -> 1425.57 | C20: =LYRA_ABO*NB_MOIS -> 360 | D20: =LYRA_ENT -> 99 | E20: =SUM(B20:D20) -> 1884.57 | F20: =E20*(1+TVA) -> 2261.484 | G20: =RANK(E20,$E$18:$E$25,1) -> 8
A21: Monetico (sans abo) | B21: =$E$16*MON1_PCT+$B$16*MON1_FIX -> 294.275 | C21: =MON1_ABO*NB_MOIS -> 0 | D21: =MON1_ENT -> 0 | E21: =SUM(B21:D21) -> 294.275 | F21: =E21*(1+TVA) -> 353.13 | G21: =RANK(E21,$E$18:$E$25,1) -> 2
A22: Monetico (abo estimé) | B22: =$E$16*MON2_PCT+$B$16*MON2_FIX -> 294.275 | C22: =MON2_ABO*NB_MOIS -> 180 | D22: =MON2_ENT -> 0 | E22: =SUM(B22:D22) -> 474.275 | F22: =E22*(1+TVA) -> 569.13 | G22: =RANK(E22,$E$18:$E$25,1) -> 3
A23: SogeCommerce Lite | B23: =$E$16*SOGEL_PCT+$B$16*SOGEL_FIX -> 294.275 | C23: =SOGEL_ABO*NB_MOIS -> 144 | D23: =SOGEL_ENT -> 100 | E23: =SUM(B23:D23) -> 538.275 | F23: =E23*(1+TVA) -> 645.93 | G23: =RANK(E23,$E$18:$E$25,1) -> 4
A24: SogeCommerce Complet | B24: =$E$16*SOGEC_PCT+$B$16*SOGEC_FIX -> 294.275 | C24: =SOGEC_ABO*NB_MOIS -> 297 | D24: =SOGEC_ENT -> 300 | E24: =SUM(B24:D24) -> 891.275 | F24: =E24*(1+TVA) -> 1069.53 | G24: =RANK(E24,$E$18:$E$25,1) -> 5
A25: HelloAsso | B25: =$E$16*HELLO_PCT+$B$16*HELLO_FIX -> 0 | C25: =HELLO_ABO*NB_MOIS -> 0 | D25: =HELLO_ENT -> 0 | E25: =SUM(B25:D25) -> 0 | F25: =E25*(1+TVA) -> 0 | G25: =RANK(E25,$E$18:$E$25,1) -> 1
A27: Scénario Fort
A28: Transactions pilote | B28: =NB_FORT*TXPA_TOT+BDETX_TOT+EPITX_TOT -> 4658 | D28: Volume rechargé pilote | E28: =NB_FORT*TXPA_TOT*MT_FORT+BDEVOL_TOT+EPIVOL_TOT -> 113855
A29: Solution | B29: Coût variable HT | C29: Abonnements HT (9 mois) | D29: Entrée one-shot HT | E29: Total HT | F29: Total TTC | G29: Rang
A30: Stripe | B30: =$E$28*STRIPE_PCT+$B$28*STRIPE_FIX -> 2872.325 | C30: =STRIPE_ABO*NB_MOIS -> 0 | D30: =STRIPE_ENT -> 0 | E30: =SUM(B30:D30) -> 2872.325 | F30: =E30*(1+TVA) -> 3446.79 | G30: =RANK(E30,$E$30:$E$37,1) -> 7
A31: Payplug | B31: =$E$28*PAYPLUG_PCT+$B$28*PAYPLUG_FIX -> 2416.905 | C31: =PAYPLUG_ABO*NB_MOIS -> 270 | D31: =PAYPLUG_ENT -> 0 | E31: =SUM(B31:D31) -> 2686.905 | F31: =E31*(1+TVA) -> 3224.286 | G31: =RANK(E31,$E$30:$E$37,1) -> 6
A32: Lyra Collect | B32: =$E$28*LYRA_PCT+$B$28*LYRA_FIX -> 2525.57 | C32: =LYRA_ABO*NB_MOIS -> 360 | D32: =LYRA_ENT -> 99 | E32: =SUM(B32:D32) -> 2984.57 | F32: =E32*(1+TVA) -> 3581.484 | G32: =RANK(E32,$E$30:$E$37,1) -> 8
A33: Monetico (sans abo) | B33: =$E$28*MON1_PCT+$B$28*MON1_FIX -> 569.275 | C33: =MON1_ABO*NB_MOIS -> 0 | D33: =MON1_ENT -> 0 | E33: =SUM(B33:D33) -> 569.275 | F33: =E33*(1+TVA) -> 683.13 | G33: =RANK(E33,$E$30:$E$37,1) -> 2
A34: Monetico (abo estimé) | B34: =$E$28*MON2_PCT+$B$28*MON2_FIX -> 569.275 | C34: =MON2_ABO*NB_MOIS -> 180 | D34: =MON2_ENT -> 0 | E34: =SUM(B34:D34) -> 749.275 | F34: =E34*(1+TVA) -> 899.13 | G34: =RANK(E34,$E$30:$E$37,1) -> 3
A35: SogeCommerce Lite | B35: =$E$28*SOGEL_PCT+$B$28*SOGEL_FIX -> 569.275 | C35: =SOGEL_ABO*NB_MOIS -> 144 | D35: =SOGEL_ENT -> 100 | E35: =SUM(B35:D35) -> 813.275 | F35: =E35*(1+TVA) -> 975.93 | G35: =RANK(E35,$E$30:$E$37,1) -> 4
A36: SogeCommerce Complet | B36: =$E$28*SOGEC_PCT+$B$28*SOGEC_FIX -> 569.275 | C36: =SOGEC_ABO*NB_MOIS -> 297 | D36: =SOGEC_ENT -> 300 | E36: =SUM(B36:D36) -> 1166.275 | F36: =E36*(1+TVA) -> 1399.53 | G36: =RANK(E36,$E$30:$E$37,1) -> 5
A37: HelloAsso | B37: =$E$28*HELLO_PCT+$B$28*HELLO_FIX -> 0 | C37: =HELLO_ABO*NB_MOIS -> 0 | D37: =HELLO_ENT -> 0 | E37: =SUM(B37:D37) -> 0 | F37: =E37*(1+TVA) -> 0 | G37: =RANK(E37,$E$30:$E$37,1) -> 1
A40: Synthèse Total TTC (source graphique)
A41: Scénario | B41: Stripe | C41: Payplug | D41: Lyra Collect | E41: Monetico (sans abo) | F41: Monetico (abo estimé) | G41: SogeCommerce Lite | H41: SogeCommerce Complet | I41: HelloAsso
A42: Faible | B42: =F6 -> 773.79 | C42: =F7 -> 1000.086 | D42: =F8 -> 1218.684 | E42: =F9 -> 122.13 | F42: =F10 -> 338.13 | G42: =F11 -> 414.93 | H42: =F12 -> 838.53 | I42: =F13 -> 0
A43: Moyen | B43: =F18 -> 1961.79 | C43: =F19 -> 2003.286 | D43: =F20 -> 2261.484 | E43: =F21 -> 353.13 | F43: =F22 -> 569.13 | G43: =F23 -> 645.93 | H43: =F24 -> 1069.53 | I43: =F25 -> 0
A44: Fort | B44: =F30 -> 3446.79 | C44: =F31 -> 3224.286 | D44: =F32 -> 3581.484 | E44: =F33 -> 683.13 | F44: =F34 -> 899.13 | G44: =F35 -> 975.93 | H44: =F36 -> 1399.53 | I44: =F37 -> 0

Sheet Graphiques
A1: GRAPHIQUES — liés aux feuilles de calcul, mis à jour automatiquement

Sheet Résumé
A1: RÉSUMÉ & RECOMMANDATION — scénario moyen du pilote, mis à jour automatiquement
A3: Solution | B3: Coût total pilote TTC | C3: Rang | D3: Verdict | E3: Point de vigilance
A4: Stripe | B4: ='Total pilote (3 scénarios)'!F18 -> 1961.79 | C4: =RANK(B4,$B$4:$B$11,1) -> 6 | D4: =IF(C4=1,"Recommandé",IF(C4<=3,"À étudier","Plus coûteux")) -> Plus coûteux | E4: Acteur américain, frais plus élevés mais zéro coût fixe
A5: Payplug | B5: ='Total pilote (3 scénarios)'!F19 -> 2003.286 | C5: =RANK(B5,$B$4:$B$11,1) -> 7 | D5: =IF(C5=1,"Recommandé",IF(C5<=3,"À étudier","Plus coûteux")) -> Plus coûteux | E5: Abonnement dû même les mois creux
A6: Lyra Collect | B6: ='Total pilote (3 scénarios)'!F20 -> 2261.484 | C6: =RANK(B6,$B$4:$B$11,1) -> 8 | D6: =IF(C6=1,"Recommandé",IF(C6<=3,"À étudier","Plus coûteux")) -> Plus coûteux | E6: Abonnement + entrée 99 € : coût de démarrage le plus lourd des PSP
A7: Monetico (sans abo) | B7: ='Total pilote (3 scénarios)'!F21 -> 353.13 | C7: =RANK(B7,$B$4:$B$11,1) -> 2 | D7: =IF(C7=1,"Recommandé",IF(C7<=3,"À étudier","Plus coûteux")) -> À étudier | E7: Nécessite un compte CM/CIC · taux 0,5 % = hypothèse
A8: Monetico (abo estimé) | B8: ='Total pilote (3 scénarios)'!F22 -> 569.13 | C8: =RANK(B8,$B$4:$B$11,1) -> 3 | D8: =IF(C8=1,"Recommandé",IF(C8<=3,"À étudier","Plus coûteux")) -> À étudier | E8: Nécessite un compte CM/CIC · abo et taux = hypothèses
A9: SogeCommerce Lite | B9: ='Total pilote (3 scénarios)'!F23 -> 645.93 | C9: =RANK(B9,$B$4:$B$11,1) -> 4 | D9: =IF(C9=1,"Recommandé",IF(C9<=3,"À étudier","Plus coûteux")) -> Plus coûteux | E9: Nécessite un compte Société Générale · taux = hypothèse · entrée 100 €
A10: SogeCommerce Complet | B10: ='Total pilote (3 scénarios)'!F24 -> 1069.53 | C10: =RANK(B10,$B$4:$B$11,1) -> 5 | D10: =IF(C10=1,"Recommandé",IF(C10<=3,"À étudier","Plus coûteux")) -> Plus coûteux | E10: Entrée 300 € one-shot · nécessite compte SG
A11: HelloAsso | B11: ='Total pilote (3 scénarios)'!F25 -> 0 | C11: =RANK(B11,$B$4:$B$11,1) -> 1 | D11: =IF(C11=1,"Recommandé",IF(C11<=3,"À étudier","Plus coûteux")) -> Recommandé | E11: CGU à valider pour le cas wallet · écran pourboire imposé
A14: Recommandation automatique (la moins chère du scénario moyen) :
A15: =INDEX(A4:A11,MATCH(MIN(B4:B11),B4:B11,0))&" — "&TEXT(MIN(B4:B11),"# ##0")&" € TTC sur le pilote. Vérifier les points de vigilance avant décision." -> HelloAsso — 0 € TTC sur le pilote. Vérifier les points de vigilance avant décision.
